LICENSE
README.md
setup.py
CVE_2017_7269.egg-info/PKG-INFO
CVE_2017_7269.egg-info/SOURCES.txt
CVE_2017_7269.egg-info/dependency_links.txt
CVE_2017_7269.egg-info/entry_points.txt
CVE_2017_7269.egg-info/requires.txt
CVE_2017_7269.egg-info/top_level.txt
cve20177269/__init__.py
cve20177269/main.py
cve20177269/includes/__init__.py
cve20177269/includes/bot.py
cve20177269/includes/filereader.py
cve20177269/includes/scan.py
cve20177269/includes/writefile.py
cve20177269/utils/__init__.py
cve20177269/utils/configure.py
cve20177269/utils/const.py
cve20177269/utils/helpers.py
cve20177269/utils/status.py