Metadata-Version: 2.1
Name: CVE-2017-7269
Version: 0.0.2
Author: @karthithehacker
Author-email: <contact@karthithehacker.com>
Classifier: Development Status :: 1 - Planning
Classifier: Intended Audience :: Developers
Classifier: Programming Language :: Python :: 3
Classifier: Operating System :: Unix
Classifier: Operating System :: MacOS :: MacOS X
Classifier: Operating System :: Microsoft :: Windows
License-File: LICENSE
